wattaged/__init__.py
wattaged/__main__.py
wattaged-0.1.1.dist-info/LICENCE.txt
wattaged-0.1.1.dist-info/METADATA
wattaged-0.1.1.dist-info/WHEEL
wattaged-0.1.1.dist-info/entry_points.txt
wattaged-0.1.1.dist-info/top_level.txt
wattaged-0.1.1.dist-info/RECORD
