Metadata-Version: 2.1
Name: wattaged
Version: 0.1.1
Summary: wattaged is a utility that logs the consummed electricity and allows you to quickly compute the consummed kWh
Home-page: https://github.com/sam1902/wattaged
Author: Samuel Prevost
Author-email: samuel.prevost@pm.me
License: BSD
Platform: UNKNOWN
Classifier: License :: OSI Approved :: BSD License
Classifier: Programming Language :: Python :: 3
Classifier: Programming Language :: Python :: 3.8
Requires-Dist: pandas
